axonate_esign_sdk-1.2.1.dist-info/licenses/LICENSE
esign_sdk/__init__.py
esign_sdk/constants.py
esign_sdk/pdf_factory_native.py
esign_sdk/sdk.py
esign_sdk/xml_request_factory.py
esign_sdk/lib/native/pdf_core.dll
esign_sdk/lib/native/pdf_core_lic.dll
esign_sdk/lib/native/pdf_signer.dll
axonate_esign_sdk-1.2.1.dist-info/METADATA
axonate_esign_sdk-1.2.1.dist-info/WHEEL
axonate_esign_sdk-1.2.1.dist-info/top_level.txt
axonate_esign_sdk-1.2.1.dist-info/RECORD
