Metadata-Version: 2.4
Name: axonate-esign-sdk
Version: 1.2.1
Summary: Python SDK for Indian eSign (Digital Signature) Integration
Home-page: https://axonatetech.com/
Author: Axonate Tech
Author-email: Axonate Tech <info@axonatetech.com>
License: MIT
Project-URL: Homepage, https://axonatetech.com/
Keywords: esign,digital-signature,india,aadhaar,pdf-signing,cryptography,axonate
Classifier: Development Status :: 5 - Production/Stable
Classifier: Intended Audience :: Developers
Classifier: Topic :: Software Development :: Libraries :: Python Modules
Classifier: Topic :: Security :: Cryptography
Classifier: License :: OSI Approved :: MIT License
Classifier: Programming Language :: Python :: 3
Classifier: Programming Language :: Python :: 3.8
Classifier: Programming Language :: Python :: 3.9
Classifier: Programming Language :: Python :: 3.10
Classifier: Programming Language :: Python :: 3.11
Classifier: Programming Language :: Python :: 3.12
Requires-Python: >=3.8
License-File: LICENSE
Requires-Dist: PyPDF2>=3.0.0
Requires-Dist: reportlab>=4.0.0
Requires-Dist: lxml>=4.9.0
Requires-Dist: cryptography>=41.0.0
Requires-Dist: requests>=2.31.0
Provides-Extra: dev
Requires-Dist: pytest>=7.0.0; extra == "dev"
Requires-Dist: pytest-cov>=4.0.0; extra == "dev"
Requires-Dist: black>=23.0.0; extra == "dev"
Provides-Extra: xml-signing
Requires-Dist: managex-xml-sdk>=1.0.0; extra == "xml-signing"
Dynamic: author
Dynamic: home-page
Dynamic: license-file
Dynamic: requires-python
